experitur/__init__.py
experitur/_version.py
experitur/cli.py
experitur/context.py
experitur/dox.py
experitur/errors.py
experitur/experiment.py
experitur/recursive_formatter.py
experitur/trial.py
experitur/helpers/__init__.py
experitur/helpers/dumper.py
experitur/helpers/merge_dicts.py
experitur/helpers/tqdm_redirect.py
experitur-1.1.0.dist-info/LICENSE
experitur-1.1.0.dist-info/METADATA
experitur-1.1.0.dist-info/WHEEL
experitur-1.1.0.dist-info/entry_points.txt
experitur-1.1.0.dist-info/top_level.txt
experitur-1.1.0.dist-info/RECORD
