Metadata-Version: 2.1
Name: experitur
Version: 1.1.0
Summary: Automates machine learning and other computer experiments
Home-page: https://github.com/moi90/experitur
Author: Simon-Martin Schroeder
Author-email: martin.schroeder@nerdluecht.de
License: UNKNOWN
Platform: UNKNOWN
Classifier: Programming Language :: Python :: 3
Classifier: Programming Language :: Python :: 3.5
Classifier: Programming Language :: Python :: 3.6
Classifier: Programming Language :: Python :: 3.7
Classifier: License :: OSI Approved :: MIT License
Classifier: Operating System :: OS Independent
Classifier: Development Status :: 3 - Alpha
Classifier: Intended Audience :: Science/Research
Requires-Python: >=3.5
Requires-Dist: Click
Requires-Dist: regex
Requires-Dist: tqdm
Requires-Dist: pyyaml
Requires-Dist: pandas
